{
  "collectionName": "components_shared_testimonial_cards",
  "info": {
    "displayName": "TestimonialCard"
  },
  "options": {},
  "attributes": {
    "Testimonial": {
      "type": "text",
      "required": true
    },
    "Image": {
      "type": "media",
      "multiple": false,
      "required": true,
      "allowedTypes": [
        "images",
        "files",
        "videos",
        "audios"
      ]
    },
    "Name": {
      "type": "string",
      "required": true
    },
    "Designation": {
      "type": "text"
    }
  },
  "config": {}
}
